Workbook

Sheet Financial Statement Amazon
A1: Financial Statement for: AMAZON.COM INC
A2: Fiscal Years: 2021 to 2024
B3: 2021 | C3: 2022 | D3: 2023 | E3: 2024
A5: BALANCE SHEET
A6: ASSETS
A7: Cash and Short-Term Investments | B7: 96291 | C7: 70384 | D7: 87277 | E7: 101449
A8: Cash | B8: 36220 | C8: 53888 | D8: 73387 | E8: 78779
A9: Short-Term Investments | B9: 60071 | C9: 16496 | D9: 13890 | E9: 22670
A10: Receivables | B10: 26500 | C10: 34800 | D10: 46900 | E10: 49300
A11: Receivables - Trade | B11: 26500 | C11: 34800 | D11: 43600 | E11: 45900
A12: Income Tax Refund | B12: 0 | C12: 0 | D12: 0 | E12: 0
A13: Current Receivables - Other | B13: 0 | C13: 0 | D13: 3300 | E13: 3400
A14: Inventories - Total | B14: 31758 | C14: 33457 | D14: 32326 | E14: 33216
A15: Inventories - Raw Materials | B15: 0 | C15: 0 | D15: 0 | E15: 0
A16: Inventories - Work in Process | B16: 0 | C16: 0 | D16: 0 | E16: 0
A17: Inventories - Finished Goods | B17: 31758 | C17: 33457 | D17: 32326 | E17: 33216
A18: Inventories - Other | B18: 0 | C18: 0 | D18: 0 | E18: 0
A19: Current Assets - Other | B19: 7031 | C19: 8150 | D19: 5848 | E19: 6902
A20: Prepaid Expense | B20: 0 | C20: 0 | D20: . | E20: .
A21: Other Curr.Asst, Excl.Ppd.Exp. | B21: 7031 | C21: 8150 | D21: 5848 | E21: 6902
A22: Current Assets - Total | B22: 161580 | C22: 146791 | D22: 172351 | E22: 190867
A23: Prop.Plant & Equip.- Total (Net) | B23: 216363 | C23: 252838 | D23: 276690 | E23: 328806
A24: P.P.& E.- Total (Gross) | B24: 294882 | C24: 349853 | D24: 396801 | E24: 470196
A25: Deprec.Depl.& Amort. | B25: 78519 | C25: 97015 | D25: 120111 | E25: 141390
A26: Invest. & Advances - Eq.Meth. | B26: . | C26: . | D26: . | E26: .
A27: Invest. & Advances - Other | B27: 6700 | C27: 4300 | D27: 5900 | E27: 20000
A28: Intangibles | B28: 20478 | C28: 26385 | D28: 30476 | E28: 31676
A29: Assets - Other | B29: 15428 | C29: 32361 | D29: 42437 | E29: 53545
A30: Deferred Charges | B30: 0 | C30: 0 | D30: 0 | E30: 0
A31: Other Asst., Excl.Def.Chg. | B31: 15428 | C31: 32361 | D31: 42437 | E31: 53545
A32: Assets - Total | B32: 420549 | C32: 462675 | D32: 527854 | E32: 624894
A33: LIABILITIES
A34: Debt in Current Liabilities | B34: 17162 | C34: 23120 | D34: 19561 | E34: 17401
A35: Notes Payable | B35: 1043 | C35: 8000 | D35: 147 | E35: 151
A36: Debt - Due in One Year | B36: 16119 | C36: 15120 | D36: 19414 | E36: 17250
A37: Accounts Payable | B37: 78664 | C37: 79600 | D37: 84981 | E37: 94363
A38: Income Taxes Payable | B38: 0 | C38: 0 | D38: 0 | E38: 0
A39: Current Liabilities - Other | B39: 46440 | C39: 52673 | D39: 60375 | E39: 67667
A40: Accrued Expense | B40: . | C40: . | D40: . | E40: .
A41: Other Curr.Liab., Excl.Accr.Exp. | B41: 46440 | C41: 52673 | D41: 60375 | E41: 67667
A42: Current Liabilities - Total | B42: 142266 | C42: 155393 | D42: 164917 | E42: 179431
A43: Long-Term Debt - Total | B43: 122595 | C43: 146818 | D43: 142211 | E43: 138000
A44: Debt - Convertible (Total) | B44: 0 | C44: 0 | D44: 0 | E44: 0
A45: Debt - Subordinated Convertible | B45: 0 | C45: 0 | D45: 0 | E45: 0
A46: Debt - Senior Convertible | B46: 0 | C46: 0 | D46: 0 | E46: 0
A47: Debt - Subordinated | B47: 0 | C47: 0 | D47: 0 | E47: 0
A48: Debt - Notes | B48: 49750 | C48: 69500 | D48: 66500 | E48: 58000
A49: Debt - Debentures | B49: 0 | C49: 0 | D49: 0 | E49: 0
A50: Long-Term Debt - Other | B50: 65529 | C50: 77048 | D50: 83390 | E50: 87008
A51: Debt - Cap. Lease Oblig. | B51: 23753 | C51: 15783 | D51: 12109 | E51: 10602
A52: Liabilities - Other | B52: 17443 | C52: 14421 | D52: 18851 | E52: 21493
A53: Def. Taxes and Invest.Tax Cred. | B53: . | C53: . | D53: . | E53: .
A54: Deferred Taxes | B54: . | C54: . | D54: . | E54: .
A55: Investment Tax Credit | B55: 0 | C55: 0 | D55: 0 | E55: 0
A56: Noncontrolling Interest - Redeemable | B56: 0 | C56: 0 | D56: 0 | E56: 0
A57: Liabilities - Total | B57: . | C57: =C70-C69 -> 316632 | D57: =D70-D69 -> 325979 | E57: =E70-E69 -> 338924
A58: SHAREHOLDERS' EQUITY
A59: Preferred Stock - Carrying Value | B59: 0 | C59: 0 | D59: 0 | E59: 0
A60: Pref. Stock - Redeemable | B60: 0 | C60: 0 | D60: 0 | E60: 0
A61: Pref. Stock - Nonredeemable | B61: 0 | C61: 0 | D61: 0 | E61: 0
A62: Common Equity - Total | B62: 138245 | C62: 146043 | D62: 201875 | E62: 285970
A63: Common Stock | B63: 5 | C63: 108 | D63: 109 | E63: 111
A64: Capital Surplus | B64: 55538 | C64: 75066 | D64: 99025 | E64: 120864
A65: Retained Earnings | B65: 84539 | C65: 78706 | D65: 110578 | E65: 172832
A66: Less: Treas.Stock - Total $ Amt. | B66: 1837 | C66: 7837 | D66: 7837 | E66: 7837
A67: Shareholders Equity - Parent | B67: 138245 | C67: 146043 | D67: 201875 | E67: 285970
A68: Noncontrolling Interest - Nonredeemable | B68: 0 | C68: 0 | D68: 0 | E68: 0
A69: Shareholders Equity - Total | B69: 138245 | C69: 146043 | D69: 201875 | E69: 285970
A70: Total Liabilities and Shareholders Equity | B70: 420549 | C70: 462675 | D70: 527854 | E70: 624894
A72: INCOME STATEMENT
A73: Sales (Net) | B73: 469822 | C73: 513983 | D73: 574785 | E73: 637959
A74: Cost of Goods Sold | B74: 249435 | C74: 263907 | D74: 274514 | E74: 294221
A75: Selling, General, and Administrative Expense | B75: 172537 | C75: 211641 | D75: 232427 | E75: 242315
A76: Operating Income Before Depreciation | B76: 47850 | C76: 38435 | D76: 67844 | E76: 101423
A77: Depreciation and Amortization | B77: 23421 | C77: 25528 | D77: 30931 | E77: 31985
A78: Amortization of Intangibles | B78: 512 | C78: 604 | D78: 706 | E78: 838
A79: Depreciation Expense (Schedule VI) | B79: . | C79: . | D79: . | E79: .
A80: Depletion Expense (Schedule VI) | B80: . | C80: . | D80: . | E80: .
A81: Operating Income After Depreciation | B81: 24429 | C81: 12907 | D81: 36913 | E81: 69438
A82: Interest Expense | B82: 1809 | C82: 2367 | D82: 3182 | E82: 2406
A83: Nonoperating Income (Expense) | B83: 15535 | C83: -15379 | D83: 3814 | E83: 2401
A84: Nonoperating Income (Expense) - Excluding Interest Income | B84: 15087 | C84: -16368 | D84: 865 | E84: -2276
A85: Interest Income | B85: 448 | C85: 989 | D85: 2949 | E85: 4677
A86: Special Items | B86: . | C86: -1100 | D86: 0 | E86: -920
A87: Pretax Income | B87: 38155 | C87: -5939 | D87: 37545 | E87: 68513
A88: Pretax Income - Domestic | B88: 35879 | C88: -8225 | D88: 32328 | E88: 61947
A89: Pretax Income - Foreign | B89: 2272 | C89: 2289 | D89: 5229 | E89: 6667
A90: Income Taxes - Total | B90: 4791 | C90: -3217 | D90: 7120 | E90: 9265
A91: Deferred Taxes (Income Account) | B91: -310 | C91: -8148 | D91: -5876 | E91: -4648
A92: Deferred Taxes - Federal | B92: 155 | C92: -6686 | D92: -5505 | E92: -4101
A93: Deferred Taxes - Foreign | B93: -287 | C93: -160 | D93: 127 | E93: -94
A94: Deferred Taxes - State | B94: -178 | C94: -1302 | D94: -498 | E94: -453
A95: Income Taxes - Federal | B95: 2129 | C95: 2175 | D95: 8652 | E95: 9039
A96: Income Taxes - Foreign | B96: 2209 | C96: 1682 | D96: 2186 | E96: 2765
A97: Income Taxes - State | B97: 763 | C97: 1074 | D97: 2158 | E97: 2109
A98: Income Taxes - Other | B98: 0 | C98: 0 | D98: 0 | E98: 0
... A109: Net Income (Loss) | B109: 33364 | C109: -2722 | D109: 30425 | E109: 59248
A111: STATEMENT OF CASH FLOWS
A112: INDIRECT OPERATING ACTIVITIES
A113: Income Before Extraordinary Items | B113: 33364 | C113: -2722 | D113: 30425 | E113: 59248
...

Sheet Financial Statement Walmart
A1: Financial Statement for: WALMART INC
A2: Fiscal Years: 2021 to 2024
B3: 2021 | C3: 2022 | D3: 2023 | E3: 2024
A5: BALANCE SHEET
A6: ASSETS
A7: Cash and Short-Term Investments | B7: 14760 | C7: 8625 | D7: 9867 | E7: 9037
A8: Cash | B8: . | C8: . | D8: . | E8: .
A9: Short-Term Investments | B9: . | C9: . | D9: . | E9: .
A10: Receivables | B10: 8280 | C10: 7933 | D10: 8796 | E10: 9975
A11: Receivables - Trade | B11: 8280 | C11: 7933 | D11: 8796 | E11: 9975
A12: Income Tax Refund | B12: 0 | C12: 0 | D12: 0 | E12: 0
A13: Current Receivables - Other | B13: 0 | C13: 0 | D13: 0 | E13: 0
A14: Inventories - Total | B14: 56511 | C14: 56576 | D14: 54892 | E14: 56435
A15: Inventories - Raw Materials | B15: . | C15: . | D15: . | E15: .
A16: Inventories - Work in Process | B16: . | C16: . | D16: . | E16: .
A17: Inventories - Finished Goods | B17: . | C17: . | D17: . | E17: .
A18: Inventories - Other | B18: . | C18: . | D18: . | E18: .
A19: Current Assets - Other | B19: 1519 | C19: 2521 | D19: 3322 | E19: 4011
A20: Prepaid Expense | B20: . | C20: . | D20: . | E20: .
A21: Other Curr.Asst, Excl.Ppd.Exp. | B21: 1519 | C21: 2521 | D21: 3322 | E21: 4011
A22: Current Assets - Total | B22: 81070 | C22: 75655 | D22: 76877 | E22: 79458
A23: Prop.Plant & Equip.- Total (Net) | B23: 112624 | C23: 119234 | D23: 130338 | E23: 139704
A24: P.P.& E.- Total (Gross) | B24: 207433 | C24: 220844 | D24: 239387 | E24: 251328
A25: Deprec.Depl.& Amort. | B25: 94809 | C25: 101610 | D25: 109049 | E25: 111624
A26: Invest. & Advances - Eq.Meth. | B26: . | C26: . | D26: . | E26: .
A27: Invest. & Advances - Other | B27: 12888 | C27: 11169 | D27: 8449 | E27: 4241
A28: Intangibles | B28: 33814 | C28: 32474 | D28: 32213 | E28: 33292
A29: Assets - Other | B29: 4464 | C29: 4665 | D29: 4522 | E29: 4128
A30: Deferred Charges | B30: . | C30: . | D30: . | E30: .
A31: Other Asst., Excl.Def.Chg. | B31: 4464 | C31: 4665 | D31: 4522 | E31: 4128
A32: Assets - Total | B32: 244860 | C32: 243197 | D32: 252399 | E32: 260823
A33: LIABILITIES
A34: Debt in Current Liabilities | B34: 5207 | C34: 6603 | D34: 6537 | E34: 7965
A35: Notes Payable | B35: 410 | C35: 372 | D35: 878 | E35: 3068
A36: Debt - Due in One Year | B36: 4797 | C36: 6231 | D36: 5659 | E36: 4897
A37: Accounts Payable | B37: 55261 | C37: 53742 | D37: 56812 | E37: 58666
A38: Income Taxes Payable | B38: 851 | C38: 727 | D38: 307 | E38: 608
A39: Current Liabilities - Other | B39: 26060 | C39: 31126 | D39: 28759 | E39: 29345
A40: Accrued Expense | B40: 23480 | C40: 25689 | D40: 26095 | E40: 26590
A41: Other Curr.Liab., Excl.Accr.Exp. | B41: 2580 | C41: 5437 | D41: 2664 | E41: 2755
A42: Current Liabilities - Total | B42: 87379 | C42: 92198 | D42: 92415 | E42: 96584
A43: Long-Term Debt - Total | B43: 52116 | C43: 52320 | D43: 54784 | E43: 52149
A44: Debt - Convertible (Total) | B44: 0 | C44: 0 | D44: 0 | E44: 0
A45: Debt - Subordinated Convertible | B45: 0 | C45: 0 | D45: 0 | E45: 0
... A57: Liabilities - Total | B57: 152969 | C57: 159443 | D57: 162050 | E57: 163402
A58: SHAREHOLDERS' EQUITY
A59: Preferred Stock - Carrying Value | B59: 0 | C59: 0 | D59: 0 | E59: 0
A60: Pref. Stock - Redeemable | B60: 0 | C60: 0 | D60: 0 | E60: 0
A61: Pref. Stock - Nonredeemable | B61: 0 | C61: 0 | D61: 0 | E61: 0
A62: Common Equity - Total | B62: 83253 | C62: 76693 | D62: 83861 | E62: 91013
A63: Common Stock | B63: 276 | C63: 269 | D63: 268 | E63: 802
A64: Capital Surplus | B64: 4839 | C64: 4969 | D64: 5081 | E64: 5503
A65: Retained Earnings | B65: 78138 | C65: 71455 | D65: 78512 | E65: 84708
A66: Less: Treas.Stock - Total $ Amt. | B66: 0 | C66: 0 | D66: 0 | E66: 0
A67: Shareholders Equity - Parent | B67: 83253 | C67: 76693 | D67: 83861 | E67: 91013
A68: Noncontrolling Interest - Nonredeemable | B68: 8638 | C68: 7061 | D68: 6488 | E68: 6408
A69: Shareholders Equity - Total | B69: 91891 | C69: 83754 | D69: 90349 | E69: 97421
A70: Total Liabilities and Shareholders Equity | B70: 244860 | C70: 243197 | D70: 252399 | E70: 260823
A72: INCOME STATEMENT
A73: Sales (Net) | B73: 569962 | C73: 608481 | D73: 645737 | E73: 680985
A74: Cost of Goods Sold | B74: 418342 | C74: 452776 | D74: 478289 | E74: 498780
A75: Selling, General, and Administrative Expense | B75: 115204 | C75: 122966 | D75: 130878 | E75: 139728
A76: Operating Income Before Depreciation | B76: 36416 | C76: 32739 | D76: 36570 | E76: 42477
A77: Depreciation and Amortization | B77: 10658 | C77: 10945 | D77: 11853 | E77: 12973
A78: Amortization of Intangibles | B78: . | C78: . | D78: . | E78: .
A79: Depreciation Expense (Schedule VI) | B79: . | C79: . | D79: . | E79: .
A80: Depletion Expense (Schedule VI) | B80: . | C80: . | D80: . | E80: .
A81: Operating Income After Depreciation | B81: 25758 | C81: 21794 | D81: 24717 | E81: 29504
A82: Interest Expense | B82: 1994 | C82: 2128 | D82: 2683 | E82: 2728
A83: Nonoperating Income (Expense) | B83: 383 | C83: 1124 | D83: -93 | E83: -311
A84: Nonoperating Income (Expense) - Excluding Interest Income | B84: 225 | C84: 870 | D84: -639 | E84: -794
A85: Interest Income | B85: 158 | C85: 254 | D85: 546 | E85: 483
A86: Special Items | B86: -5451 | C86: -3774 | D86: -93 | E86: -156
A87: Pretax Income | B87: 18696 | C87: 17016 | D87: 21848 | E87: 26309
A88: Pretax Income - Domestic | B88: 15536 | C88: 15089 | D88: 20092 | E88: 18571
A89: Pretax Income - Foreign | B89: 3160 | C89: 1927 | D89: 1756 | E89: 7738
A90: Income Taxes - Total | B90: 4756 | C90: 5724 | D90: 5578 | E90: 6152
A91: Deferred Taxes (Income Account) | B91: -759 | C91: 430 | D91: -171 | E91: -663
A92: Deferred Taxes - Federal | B92: -671 | C92: 608 | D92: -438 | E92: -214
... A109: Net Income (Loss) | B109: 13673 | C109: 11680 | D109: 15511 | E109: 19436
A111: STATEMENT OF CASH FLOWS
A112: INDIRECT OPERATING ACTIVITIES
A113: Income Before Extraordinary Items | B113: 13940 | C113: 11292 | D113: 16270 | E113: 20157
A114: Depreciation and Amortization | B114: 10658 | C114: 10945 | D114: 11853 | E114: 12973
A115: Extraordinary Items and Discontinued Operations | B115: 0 | C115: 0 | D115: 0 | E115: 0
A116: Deferred Taxes | B116: -755 | C116: 449 | D116: -175 | E116: -635
A117: Equity in Net Loss (Earnings) | B117: . | C117: . | D117: . | E117: .
A118: Sale of Property, Plant, and Equipment and Sale of Investments - Loss (Gain) | B118: 433 | C118: 0 | D118: . | E118: .
A119: Funds from Operations - Other | B119: 6502 | C119: 3602 | D119: 5835 | E119: 3767
A120: Accounts Receivable - Decrease (Increase) | B120: -1796 | C120: 240 | D120: -797 | E120: -1106
A121: Inventory - Decrease (Increase) | B121: -11764 | C121: -528 | D121: 2017 | E121: -2755
A122: Accounts Payable and Accrued Liabilities - Increase (Decrease) | B122: 6924 | C122: 2968 | D122: 1191 | E122: 3607
A123: Income Taxes - Accrued - Increase (Decrease) | B123: 39 | C123: -127 | D123: -468 | E123: 435
A124: Assets and Liablities - Other (Net Change) | B124: 0 | C124: 0 | D124: 0 | E124: 0
A125: Operating Activities - Net Cash Flow | B125: 24181 | C125: 28841 | D125: 35726 | E125: 36443
A126: INVESTING ACTIVITIES
A127: Increase in Investments | B127: 0 | C127: 0 | D127: 0 | E127: 0
A128: Sale of Investments | B128: 0 | C128: 0 | D128: 0 | E128: 4080
A129: Short-Term Investments - Change | B129: . | C129: . | D129: . | E129: .
A130: Capital Expenditures | B130: 13106 | C130: 16857 | D130: 20606 | E130: 23783
...

Sheet Key Ratios
A1: Particulars | B1: Amazon | E1: Walmart
B2: 2022 | C2: 2023 | D2: 2024 | E2: 2022 | F2: 2023 | G2: 2024
A3: Return on Equity (ROE)
A4: Net Income/(Loss) | B4: ='Financial Statement Amazon'!C109 -> -2722 | C4: ='Financial Statement Amazon'!D109 -> 30425 | D4: ='Financial Statement Amazon'!E109 -> 59248 | E4: ='Financial Statement Walmart'!C109 -> 11680 | F4: ='Financial Statement Walmart'!D109 -> 15511 | G4: ='Financial Statement Walmart'!E109 -> 19436
A5: Average Equity | B5: =AVERAGE('Financial Statement Amazon'!B69:C69) -> 142144 | C5: =AVERAGE('Financial Statement Amazon'!C69:D69) -> 173959 | D5: =AVERAGE('Financial Statement Amazon'!D69:E69) -> 243922.5 | E5: =AVERAGE('Financial Statement Walmart'!B69:C69) -> 87822.5 | F5: =AVERAGE('Financial Statement Walmart'!C69:D69) -> 87051.5 | G5: =AVERAGE('Financial Statement Walmart'!D69:E69) -> 93885
A6: ROE | B6: =B4/B5 -> -0.019149595 | C6: =C4/C5 -> 0.17489753 | D6: =D4/D5 -> 0.24289682 | E6: =E4/E5 -> 0.13299553 | F6: =F4/F5 -> 0.17818188 | G6: =G4/G5 -> 0.20701923
A8: Return on Asset (ROA)
A9: Net Income/(Loss) | B9: ='Financial Statement Amazon'!C109 -> -2722 | C9: ='Financial Statement Amazon'!D109 -> 30425 | D9: ='Financial Statement Amazon'!E109 -> 59248 | E9: =E4 -> 11680 | F9: =F4 -> 15511 | G9: =G4 -> 19436
A10: Average Total Asset | B10: =AVERAGE('Financial Statement Amazon'!B32:C32) -> 441612 | C10: =AVERAGE('Financial Statement Amazon'!C32:D32) -> 495264.5 | D10: =AVERAGE('Financial Statement Amazon'!D32:E32) -> 576374 | E10: =AVERAGE('Financial Statement Walmart'!B32:C32) -> 244028.5 | F10: =AVERAGE('Financial Statement Walmart'!C32:D32) -> 247798 | G10: =AVERAGE('Financial Statement Walmart'!D32:E32) -> 256611
A11: ROA | B11: =B9/B10 -> -0.0061637818 | C11: =C9/C10 -> 0.061431821 | D11: =D9/D10 -> 0.10279437 | E11: =E9/E10 -> 0.047863262 | F11: =F9/F10 -> 0.06259534 | G11: =G9/G10 -> 0.075741102
A13: Return on net operating assets (RNOA)
A14: Net Operating Profit After Tax | B14: ='Additional Calculation'!B10 -> 12397.34 | C14: ='Additional Calculation'!C10 -> 29925.72 | D14: ='Additional Calculation'!D10 -> 60171.95 | E14: ='Additional Calculation'!E10 -> 15859.16 | F14: ='Additional Calculation'!F10 -> 18556.04 | G14: ='Additional Calculation'!G10 -> 22713.81
A15: Average Net Operating Asset | B15: =AVERAGE('Additional Calculation'!B29:C29) -> 257710.5 | C15: =AVERAGE('Additional Calculation'!C29:D29) -> 312407.5 | D15: =AVERAGE('Additional Calculation'!D29:E29) -> 359217 | E15: =AVERAGE('Additional Calculation'!E29:F29) -> 256293 | F15: =AVERAGE('Additional Calculation'!F29:G29) -> 127140.5 | G15: =AVERAGE('Additional Calculation'!G29:H29) -> 132915.5
A16: RNOA | B16: =B14/B15 -> 0.048105684 | C16: =C14/C15 -> 0.095790658 | D16: =D14/D15 -> 0.16750864 | E16: =E14/E15 -> 0.061879021 | F16: =F14/F15 -> 0.14594909 | G16: =G14/G15 -> 0.1708891
A18: Inventory Turnover Ratio
A19: Cost of Goods Sold(COGS) | B19: ='Financial Statement Amazon'!C74 -> 263907 | C19: ='Financial Statement Amazon'!D74 -> 274514 | D19: ='Financial Statement Amazon'!E74 -> 294221 | E19: ='Financial Statement Walmart'!C74 -> 452776 | F19: ='Financial Statement Walmart'!D74 -> 478289 | G19: ='Financial Statement Walmart'!E74 -> 498780
A20: Average Inventory | B20: =AVERAGE('Financial Statement Amazon'!B14:C14) -> 32607.5 | C20: =AVERAGE('Financial Statement Amazon'!C14:D14) -> 32891.5 | D20: =AVERAGE('Financial Statement Amazon'!D14:E14) -> 32771 | E20: =AVERAGE('Financial Statement Walmart'!B14:C14) -> 56543.5 | F20: =AVERAGE('Financial Statement Walmart'!C14:D14) -> 55734 | G20: =AVERAGE('Financial Statement Walmart'!D14:E14) -> 55663.5
A21: Inventory Turnover Ratio | B21: =B19/B20 -> 8.0934448 | C21: =C19/C20 -> 8.3460469 | D21: =D19/D20 -> 8.9780904 | E21: =E19/E20 -> 8.0075694 | F21: =F19/F20 -> 8.5816378 | G21: =G19/G20 -> 8.9606295
A23: Account Recievable Turnover
A24: Sales | B24: ='Financial Statement Amazon'!C73 -> 513983 | C24: ='Financial Statement Amazon'!D73 -> 574785 | D24: ='Financial Statement Amazon'!E73 -> 637959 | E24: ='Financial Statement Walmart'!C73 -> 608481 | F24: ='Financial Statement Walmart'!D73 -> 645737 | G24: ='Financial Statement Walmart'!E73 -> 680985
A25: Average Account Recievable | B25: =AVERAGE('Financial Statement Amazon'!B10:C10) -> 30650 | C25: =AVERAGE('Financial Statement Amazon'!C10:D10) -> 40850 | D25: =AVERAGE('Financial Statement Amazon'!D10:E10) -> 48100 | E25: =AVERAGE('Financial Statement Walmart'!B10:C10) -> 8106.5 | F25: =AVERAGE('Financial Statement Walmart'!C10:D10) -> 8364.5 | G25: =AVERAGE('Financial Statement Walmart'!D10:E10) -> 9385.5
A26: ARTO | B26: =B24/B25 -> 16.769429 | C26: =C24/C25 -> 14.070624 | D26: =D24/D25 -> 13.263181 | E26: =E24/E25 -> 75.060877 | F26: =F24/F25 -> 77.199713 | G26: =G24/G25 -> 72.557136
A28: Account Payable Turnover
A29: Cost of Goods Sold | B29: ='Financial Statement Amazon'!C74 -> 263907 | C29: ='Financial Statement Amazon'!D74 -> 274514 | D29: ='Financial Statement Amazon'!E74 -> 294221 | E29: ='Financial Statement Walmart'!C74 -> 452776 | F29: ='Financial Statement Walmart'!D74 -> 478289 | G29: ='Financial Statement Walmart'!E74 -> 498780
A30: Average Account Payable | B30: =AVERAGE('Financial Statement Amazon'!B37:C37) -> 79132 | C30: =AVERAGE('Financial Statement Amazon'!C37:D37) -> 82290.5 | D30: =AVERAGE('Financial Statement Amazon'!D37:E37) -> 89672 | E30: =AVERAGE('Financial Statement Walmart'!B37:C37) -> 54501.5 | F30: =AVERAGE('Financial Statement Walmart'!C37:D37) -> 55277 | G30: =AVERAGE('Financial Statement Walmart'!D37:E37) -> 57739
A31: APTO | B31: =B29/B30 -> 3.3350225 | C31: =C29/C30 -> 3.3359136 | D31: =D29/D30 -> 3.2810799 | E31: =E29/E30 -> 8.3075879 | F31: =F29/F30 -> 8.6525861 | G31: =G29/G30 -> 8.6385286
A33: PPE Turnover
A34: Sales | B34: =B24 -> 513983 | C34: =C24 -> 574785 | D34: =D24 -> 637959 | E34: =E24 -> 608481 | F34: =F24 -> 645737 | G34: =G24 -> 680985
A35: Average PPE Asset | B35: =AVERAGE('Financial Statement Amazon'!B23:C23) -> 234600.5 | C35: =AVERAGE('Financial Statement Amazon'!C23:D23) -> 264764 | D35: =AVERAGE('Financial Statement Amazon'!D23:E23) -> 302748 | E35: =AVERAGE('Financial Statement Walmart'!B23:C23) -> 115929 | F35: =AVERAGE('Financial Statement Walmart'!C23:D23) -> 124786 | G35: =AVERAGE('Financial Statement Walmart'!D23:E23) -> 135021
A36: PPETO | B36: =B34/B35 -> 2.1908862 | C36: =C34/C35 -> 2.1709334 | D36: =D34/D35 -> 2.1072278 | E36: =E34/E35 -> 5.2487385 | F36: =F34/F35 -> 5.1747552 | G36: =G34/G35 -> 5.0435488
A38: Times Interest Earned
A39: EBIT | B39: ='Financial Statement Amazon'!C81 -> 12907 | C39: ='Financial Statement Amazon'!D81 -> 36913 | D39: ='Financial Statement Amazon'!E81 -> 69438 | E39: ='Financial Statement Walmart'!C81 -> 21794 | F39: ='Financial Statement Walmart'!D81 -> 24717 | G39: ='Financial Statement Walmart'!E81 -> 29504
A40: Interest Expenses | B40: ='Financial Statement Amazon'!C82 -> 2367 | C40: ='Financial Statement Amazon'!D82 -> 3182 | D40: ='Financial Statement Amazon'!E82 -> 2406 | E40: ='Financial Statement Walmart'!C82 -> 2128 | F40: ='Financial Statement Walmart'!D82 -> 2683 | G40: ='Financial Statement Walmart'!E82 -> 2728
A41: TIE | B41: =B39/B40 -> 5.452894 | C41: =C39/C40 -> 11.600566 | D41: =D39/D40 -> 28.860349 | E41: =E39/E40 -> 10.241541 | F41: =F39/F40 -> 9.2124488 | G41: =G39/G40 -> 10.815249
A43: EBITDA Coverage Ratio
A44: EBIT+Depreciation+ Amortization | B44: =B39+'Financial Statement Amazon'!C77 -> 38435 | C44: =C39+'Financial Statement Amazon'!D77 -> 67844 | D44: =D39+'Financial Statement Amazon'!E77 -> 101423 | E44: =E39+'Financial Statement Walmart'!C77 -> 32739 | F44: =F39+'Financial Statement Walmart'!D77 -> 36570 | G44: =G39+'Financial Statement Walmart'!E77 -> 42477
A45: Interest Expenses | B45: =B40 -> 2367 | C45: =C40 -> 3182 | D45: =D40 -> 2406 | E45: =E40 -> 2128 | F45: =F40 -> 2683 | G45: =G40 -> 2728
A46: EBITDA Coverage Ratio | B46: =B44/B45 -> 16.237854 | C46: =C44/C45 -> 21.321182 | D46: =D44/D45 -> 42.154198 | E46: =E44/E45 -> 15.384868 | F46: =F44/F45 -> 13.630265 | G46: =G44/G45 -> 15.570748
A48: Operating Cashflow To Debt
A49: Cash From Operation | B49: ='Financial Statement Amazon'!C125 -> 46752 | C49: ='Financial Statement Amazon'!D125 -> 84946 | D49: ='Financial Statement Amazon'!E125 -> 115877 | E49: ='Financial Statement Walmart'!C125 -> 28841 | F49: ='Financial Statement Walmart'!D125 -> 35726 | G49: ='Financial Statement Walmart'!E125 -> 36443
A50: Short term Debt + Long Term Debt | B50: ='Additional Calculation'!B37 -> 66912 | C50: ='Additional Calculation'!C37 -> 92620 | D50: ='Additional Calculation'!D37 -> 86061 | E50: ='Additional Calculation'!E37 -> 75401 | F50: ='Additional Calculation'!F37 -> 40071 | G50: ='Additional Calculation'!G37 -> 41252
A51: =A48 -> Operating Cashflow To Debt | B51: =B49/B50 -> 0.69870875 | C51: =C49/C50 -> 0.91714532 | D51: =D49/D50 -> 1.3464519 | E51: =E49/E50 -> 0.38250156 | F51: =F49/F50 -> 0.89156747 | G51: =G49/G50 -> 0.88342383
A53: Free Cash Flow to Debt
A54: Capex | B54: ='Financial Statement Amazon'!C130 -> 63645 | C54: ='Financial Statement Amazon'!D130 -> 52729 | D54: ='Financial Statement Amazon'!E130 -> 82999 | E54: ='Financial Statement Walmart'!C130 -> 16857 | F54: ='Financial Statement Walmart'!D130 -> 20606 | G54: ='Financial Statement Walmart'!E130 -> 23783
A55: Cash From Operation - Capex | B55: =B49-B54 -> -16893 | C55: =C49-C54 -> 32217 | D55: =D49-D54 -> 32878 | E55: =E49-E54 -> 11984 | F55: =F49-F54 -> 15120 | G55: =G49-G54 -> 12660
A56: Short term Debt + Long Term Debt | B56: =B50 -> 66912 | C56: =C50 -> 92620 | D56: =D50 -> 86061 | E56: =E50 -> 75401 | F56: =F50 -> 40071 | G56: =G50 -> 41252
A57: FCFD | B57: =B55/B56 -> -0.25246593 | C57: =C55/C56 -> 0.34784064 | D57: =D55/D56 -> 0.38203135 | E57: =E55/E56 -> 0.15893688 | F57: =F55/F56 -> 0.37733024 | G57: =G55/G56 -> 0.30689421
A59: Current Ratio
A60: Current Asset | B60: ='Financial Statement Amazon'!C22 -> 146791 | C60: ='Financial Statement Amazon'!D22 -> 172351 | D60: ='Financial Statement Amazon'!E22 -> 190867 | E60: ='Financial Statement Walmart'!C22 -> 75655 | F60: ='Financial Statement Walmart'!D22 -> 76877 | G60: ='Financial Statement Walmart'!E22 -> 79458
A61: Current Liabilities | B61: ='Financial Statement Amazon'!C42 -> 155393 | C61: ='Financial Statement Amazon'!D42 -> 164917 | D61: ='Financial Statement Amazon'!E42 -> 179431 | E61: ='Financial Statement Walmart'!C42 -> 92198 | F61: ='Financial Statement Walmart'!D42 -> 92415 | G61: ='Financial Statement Walmart'!E42 -> 96584
A62: Current Ratio | B62: =B60/B61 -> 0.94464358 | C62: =C60/C61 -> 1.0450772 | D62: =D60/D61 -> 1.0637348 | E62: =E60/E61 -> 0.82057095 | F62: =F60/F61 -> 0.83186712 | G62: =G60/G61 -> 0.82268285
A64: Quick ratios
A65: Cash+Marketable Securities+Account Recievable | B65: ='Financial Statement Amazon'!C7+'Financial Statement Amazon'!C10 -> 105184 | C65: ='Financial Statement Amazon'!D7+'Financial Statement Amazon'!D10 -> 134177 | D65: ='Financial Statement Amazon'!E7+'Financial Statement Amazon'!E10 -> 150749 | E65: ='Financial Statement Walmart'!C10+'Financial Statement Walmart'!C7 -> 16558 | F65: ='Financial Statement Walmart'!D10+'Financial Statement Walmart'!D7 -> 18663 | G65: ='Financial Statement Walmart'!E10+'Financial Statement Walmart'!E7 -> 19012
A66: Current Liabilities | B66: =B61 -> 155393 | C66: =C61 -> 164917 | D66: =D61 -> 179431 | E66: =E61 -> 92198 | F66: =F61 -> 92415 | G66: =G61 -> 96584
A67: QR | B67: =B65/B66 -> 0.67689021 | C67: =C65/C66 -> 0.81360321 | D67: =D65/D66 -> 0.84015025 | E67: =E65/E66 -> 0.17959175 | F67: =F65/F66 -> 0.20194774 | G67: =G65/G66 -> 0.1968442
A69: Liabilities to Equity Ratios
A70: Total Liabilities | B70: ='Financial Statement Amazon'!C57 -> 316632 | C70: ='Financial Statement Amazon'!D57 -> 325979 | D70: ='Financial Statement Amazon'!E57 -> 338924 | E70: ='Financial Statement Walmart'!C57 -> 159443 | F70: ='Financial Statement Walmart'!D57 -> 162050 | G70: ='Financial Statement Walmart'!E57 -> 163402
A71: Stockholders Equity | B71: ='Financial Statement Amazon'!C69 -> 146043 | C71: ='Financial Statement Amazon'!D69 -> 201875 | D71: ='Financial Statement Amazon'!E69 -> 285970 | E71: ='Financial Statement Walmart'!C69 -> 83754 | F71: ='Financial Statement Walmart'!D69 -> 90349 | G71: ='Financial Statement Walmart'!E69 -> 97421
A72: LER | B72: =B70/B71 -> 2.1680738 | C72: =C70/C71 -> 1.6147567 | D72: =D70/D71 -> 1.1851733 | E72: =E70/E71 -> 1.9037061 | F72: =F70/F71 -> 1.7936004 | G72: =G70/G71 -> 1.677277
A74: Total Debt To equity Ratio
A75: Long term debt + Short term Debt | B75: =B56 -> 66912 | C75: =C56 -> 92620 | D75: =D56 -> 86061 | E75: =E56 -> 75401 | F75: =F56 -> 40071 | G75: =G56 -> 41252
A76: Stockholders Equity | B76: =B71 -> 146043 | C76: =C71 -> 201875 | D76: =D71 -> 285970 | E76: =E71 -> 83754 | F76: =F71 -> 90349 | G76: =G71 -> 97421
A77: Total Debt To equity Ratio | B77: =B75/B76 -> 0.45816643 | C77: =C75/C76 -> 0.45879876 | D77: =D75/D76 -> 0.30094415 | E77: =E75/E76 -> 0.90026745 | F77: =F75/F76 -> 0.44351349 | G77: =G75/G76 -> 0.42344053
A79: Financial Leverage
A80: Average Total Asset | B80: =B10 -> 441612 | C80: =C10 -> 495264.5 | D80: =D10 -> 576374 | E80: =E10 -> 244028.5 | F80: =F10 -> 247798 | G80: =G10 -> 256611
A81: Average Shareholder's Equity | B81: =B5 -> 142144 | C81: =C5 -> 173959 | D81: =D5 -> 243922.5 | E81: =E5 -> 87822.5 | F81: =F5 -> 87051.5 | G81: =G5 -> 93885
A82: FL | B82: =B80/B81 -> 3.1067931 | C82: =C80/C81 -> 2.8470186 | D82: =D80/D81 -> 2.362939 | E82: =E80/E81 -> 2.7786558 | F82: =F80/F81 -> 2.8465678 | G82: =G80/G81 -> 2.7332481
A84: Net Operating Profit Margin(NOPM)
A85: Net Operating Profit After Tax(NOPAT) | B85: ='Additional Calculation'!B10 -> 12397.34 | C85: ='Additional Calculation'!C10 -> 29925.72 | D85: ='Additional Calculation'!D10 -> 60171.95 | E85: ='Additional Calculation'!E10 -> 15859.16 | F85: ='Additional Calculation'!F10 -> 18556.04 | G85: ='Additional Calculation'!G10 -> 22713.81
A86: Sales | B86: =B90 -> 513983 | C86: =C90 -> 574785 | D86: =D90 -> 637959 | E86: =E34 -> 608481 | F86: =F34 -> 645737 | G86: =G34 -> 680985
A87: NOPM | B87: =B85/B86 -> 0.024120136 | C87: =C85/C86 -> 0.052064198 | D87: =D85/D86 -> 0.094319463 | E87: =E85/E86 -> 0.026063525 | F87: =F85/F86 -> 0.028736219 | G87: =G85/G86 -> 0.033354347
A89: Net Operating Asset Turnover
A90: Sales | B90: =B96 -> 513983 | C90: =C96 -> 574785 | D90: =D96 -> 637959 | E90: =E86 -> 608481 | F90: =F86 -> 645737 | G90: =G86 -> 680985
A91: Average Net Operating Assset | B91: =B15 -> 257710.5 | C91: =C15 -> 312407.5 | D91: =D15 -> 359217 | E91: =E15 -> 256293 | F91: =F15 -> 127140.5 | G91: =G15 -> 132915.5
A92: Net Operating Asset Turnover | B92: =B90/B91 -> 1.9944201 | C92: =C90/C91 -> 1.8398566 | D92: =D90/D91 -> 1.7759711 | E92: =E90/E91 -> 2.3741616 | F92: =F90/F91 -> 5.0789245 | G92: =G90/G91 -> 5.1234431
A94: Gross Profit Margin
A95: Sales-COGS | B95: ='Financial Statement Amazon'!C73-'Financial Statement Amazon'!C74 -> 250076 | C95: ='Financial Statement Amazon'!D73-'Financial Statement Amazon'!D74 -> 300271 | D95: ='Financial Statement Amazon'!E73-'Financial Statement Amazon'!E74 -> 343738 | E95: ='Financial Statement Walmart'!C73-'Financial Statement Walmart'!C74 -> 155705 | F95: ='Financial Statement Walmart'!D73-'Financial Statement Walmart'!D74 -> 167448 | G95: ='Financial Statement Walmart'!E73-'Financial Statement Walmart'!E74 -> 182205
A96: Sales | B96: =B34 -> 513983 | C96: =C34 -> 574785 | D96: =D34 -> 637959 | E96: =E34 -> 608481 | F96: =F34 -> 645737 | G96: =G34 -> 680985
A97: GPM | B97: =B95/B96 -> 0.48654527 | C97: =C95/C96 -> 0.52240577 | D97: =D95/D96 -> 0.53880892 | E97: =E95/E96 -> 0.25589131 | F97: =F95/F96 -> 0.259313 | G97: =G95/G96 -> 0.26756096
A99: Operating Expenses Margin
A100: Operating Profit After Depreciation | B100: ='Financial Statement Amazon'!C81 -> 12907 | C100: ='Financial Statement Amazon'!D81 -> 36913 | D100: ='Financial Statement Amazon'!E81 -> 69438 | E100: ='Financial Statement Walmart'!C81 -> 21794 | F100: ='Financial Statement Walmart'!D81 -> 24717 | G100: ='Financial Statement Walmart'!E81 -> 29504
A101: Sales | B101: =B34 -> 513983 | C101: =C34 -> 574785 | D101: =D34 -> 637959 | E101: =E34 -> 608481 | F101: =F34 -> 645737 | G101: =G34 -> 680985
A102: OEM | B102: =B100/B101 -> 0.025111725 | C102: =C100/C101 -> 0.064220535 | D102: =D100/D101 -> 0.10884399 | E102: =E100/E101 -> 0.035817059 | F102: =F100/F101 -> 0.038277193 | G102: =G100/G101 -> 0.043325477
A104: Profit Margin
A105: Net Income | B105: ='Financial Statement Amazon'!C109 -> -2722 | C105: ='Financial Statement Amazon'!D109 -> 30425 | D105: ='Financial Statement Amazon'!E109 -> 59248 | E105: ='Financial Statement Walmart'!C109 -> 11680 | F105: ='Financial Statement Walmart'!D109 -> 15511 | G105: ='Financial Statement Walmart'!E109 -> 19436
A106: Sales | B106: ='Financial Statement Amazon'!C73 -> 513983 | C106: ='Financial Statement Amazon'!D73 -> 574785 | D106: ='Financial Statement Amazon'!E73 -> 637959 | E106: ='Financial Statement Walmart'!C73 -> 608481 | F106: ='Financial Statement Walmart'!D73 -> 645737 | G106: ='Financial Statement Walmart'!E73 -> 680985
A107: Profit Margin | B107: =B105/B106 -> -0.005295895 | C107: =C105/C106 -> 0.052932836 | D107: =D105/D106 -> 0.092871172 | E107: =E105/E106 -> 0.019195341 | F107: =F105/F106 -> 0.024020615 | G107: =G105/G106 -> 0.02854101

Sheet Additional Calculation
A1: Particulars | B1: Amazon | E1: Walmart
B2: 2022 | C2: 2023 | D2: 2024 | E2: 2022 | F2: 2023 | G2: 2024
A3: ='Financial Statement Amazon'!A81 -> Operating Income After Depreciation | B3: ='Financial Statement Amazon'!C81 -> 12907 | C3: ='Financial Statement Amazon'!D81 -> 36913 | D3: ='Financial Statement Amazon'!E81 -> 69438 | E3: ='Financial Statement Walmart'!C81 -> 21794 | F3: ='Financial Statement Walmart'!D81 -> 24717 | G3: ='Financial Statement Walmart'!E81 -> 29504
A4: EBIT | B4: =B3 -> 12907 | C4: =C3 -> 36913 | D4: =D3 -> 69438 | E4: =E3 -> 21794 | F4: =F3 -> 24717 | G4: =G3 -> 29504
A5: (less) Tax on Operating Profit
A6: Tax Expense | B6: ='Financial Statement Amazon'!C90 -> -3217 | C6: ='Financial Statement Amazon'!D90 -> 7120 | D6: ='Financial Statement Amazon'!E90 -> 9265 | E6: ='Financial Statement Walmart'!C90 -> 5724 | F6: ='Financial Statement Walmart'!D90 -> 5578 | G6: ='Financial Statement Walmart'!E90 -> 6152
A7: Pretax non operating expense | B7: ='Financial Statement Amazon'!C82-'Financial Statement Amazon'!C83 -> 17746 | C7: ='Financial Statement Amazon'!D82-'Financial Statement Amazon'!D83 -> -632 | D7: ='Financial Statement Amazon'!E82-'Financial Statement Amazon'!E83 -> 5 | E7: ='Financial Statement Walmart'!C82-'Financial Statement Walmart'!C83 -> 1004 | F7: ='Financial Statement Walmart'!D82-'Financial Statement Walmart'!D83 -> 2776 | G7: ='Financial Statement Walmart'!E82-'Financial Statement Walmart'!E83 -> 3039
A8: Statutary Tax Rate | B8: 0.21 | C8: 0.21 | D8: 0.21 | E8: 0.21 | F8: 0.21 | G8: 0.21
B9: =B6+(B7*B8) -> 509.66 | C9: =C6+(C7*C8) -> 6987.28 | D9: =D6+(D7*D8) -> 9266.05 | E9: =E6+(E7*E8) -> 5934.84 | F9: =F6+(F7*F8) -> 6160.96 | G9: =G6+(G7*G8) -> 6790.19
A10: NOPAT | B10: =B4-B9 -> 12397.34 | C10: =C4-C9 -> 29925.72 | D10: =D4-D9 -> 60171.95 | E10: =E4-E9 -> 15859.16 | F10: =F4-F9 -> 18556.04 | G10: =G4-G9 -> 22713.81
A12: Particulars | B12: Amazon | F12: Walmart
A13: Operating Asset | B13: 2021 | C13: 2022 | D13: 2023 | E13: 2024 | F13: 2021 | G13: 2022 | H13: 2023 | I13: 2024
A14: Accounts Receivable | B14: ='Financial Statement Amazon'!B10 -> 26500 | C14: ='Financial Statement Amazon'!C10 -> 34800 | D14: ='Financial Statement Amazon'!D10 -> 46900 | E14: ='Financial Statement Amazon'!E10 -> 49300 | F14: ='Financial Statement Walmart'!B10 -> 8280 | G14: ='Financial Statement Walmart'!C10 -> 7933 | H14: ='Financial Statement Walmart'!D10 -> 8796 | I14: ='Financial Statement Walmart'!E10 -> 9975
A15: Inventories | B15: ='Financial Statement Amazon'!B14 -> 31758 | C15: ='Financial Statement Amazon'!C14 -> 33457 | D15: ='Financial Statement Amazon'!D14 -> 32326 | E15: ='Financial Statement Amazon'!E14 -> 33216 | F15: ='Financial Statement Walmart'!B14 -> 56511 | G15: ='Financial Statement Walmart'!C14 -> 56576 | H15: ='Financial Statement Walmart'!D14 -> 54892 | I15: ='Financial Statement Walmart'!E14 -> 56435
A16: Other Current Assets | B16: ='Financial Statement Amazon'!B19 -> 7031 | C16: ='Financial Statement Amazon'!C19 -> 8150 | D16: ='Financial Statement Amazon'!D19 -> 5848 | E16: ='Financial Statement Amazon'!E19 -> 6902 | F16: ='Financial Statement Walmart'!B19 -> 1519 | G16: ='Financial Statement Walmart'!C19 -> 2521 | H16: ='Financial Statement Walmart'!D19 -> 3322 | I16: ='Financial Statement Walmart'!E19 -> 4011
A17: PPE | B17: ='Financial Statement Amazon'!B23 -> 216363 | C17: ='Financial Statement Amazon'!C23 -> 252838 | D17: ='Financial Statement Amazon'!D23 -> 276690 | E17: ='Financial Statement Amazon'!E23 -> 328806 | F17: ='Financial Statement Walmart'!B23 -> 112624 | G17: ='Financial Statement Walmart'!C23 -> 119234 | H17: ='Financial Statement Walmart'!D23 -> 130338 | I17: ='Financial Statement Walmart'!E23 -> 139704
A18: Goodwill and Intangible assets. | B18: ='Financial Statement Amazon'!B28 -> 20478 | C18: ='Financial Statement Amazon'!C28 -> 26385 | D18: ='Financial Statement Amazon'!D28 -> 30476 | E18: ='Financial Statement Amazon'!E28 -> 31676 | F18: ='Financial Statement Walmart'!B28 -> 33814 | G18: ='Financial Statement Walmart'!C28 -> 32474 | H18: ='Financial Statement Walmart'!D28 -> 32213 | I18: ='Financial Statement Walmart'!E28 -> 33292
A19: Other Long-Term assets. | B19: ='Financial Statement Amazon'!B29 -> 15428 | C19: ='Financial Statement Amazon'!C29 -> 32361 | D19: ='Financial Statement Amazon'!D29 -> 42437 | E19: ='Financial Statement Amazon'!E29 -> 53545 | F19: ='Financial Statement Walmart'!B29 -> 4464 | G19: ='Financial Statement Walmart'!C29 -> 4665 | H19: ='Financial Statement Walmart'!D29 -> 4522 | I19: ='Financial Statement Walmart'!E29 -> 4128
A20: Total Operating Assets (A) | B20: =SUM(B14:B19) -> 317558 | C20: =SUM(C14:C19) -> 387991 | D20: =SUM(D14:D19) -> 434677 | E20: =SUM(E14:E19) -> 503445 | F20: =SUM(F14:F19) -> 217212 | G20: =SUM(G14:G19) -> 223403 | H20: =SUM(H14:H19) -> 234083 | I20: =SUM(I14:I19) -> 247545
A22: Operating Liabilities
A23: Accounts Payable | B23: ='Financial Statement Amazon'!B37 -> 78664 | C23: ='Financial Statement Amazon'!C37 -> 79600 | D23: ='Financial Statement Amazon'!D37 -> 84981 | E23: ='Financial Statement Amazon'!E37 -> 94363 | F23: ='Financial Statement Walmart'!B37 -> 55261 | G23: ='Financial Statement Walmart'!C37 -> 53742 | H23: ='Financial Statement Walmart'!D37 -> 56812 | I23: ='Financial Statement Walmart'!E37 -> 58666
A24: Accrued Liabilities | B24: 0 | C24: 0 | D24: 0 | E24: 0 | F24: ='Financial Statement Walmart'!B40 -> 23480 | G24: ='Financial Statement Walmart'!C40 -> 25689 | H24: ='Financial Statement Walmart'!D40 -> 26095 | I24: ='Financial Statement Walmart'!E40 -> 26590
A25: Deferred Tax Liabilities | B25: 0 | C25: 0 | D25: 0 | E25: 0 | F25: ='Financial Statement Walmart'!B54 -> 6917 | G25: ='Financial Statement Walmart'!C54 -> 7269 | H25: ='Financial Statement Walmart'!D54 -> 7248 | I25: ='Financial Statement Walmart'!E54 -> 7019
A26: Other Long term Liabilities | B26: ='Financial Statement Amazon'!B52 -> 17443 | C26: ='Financial Statement Amazon'!C52 -> 14421 | D26: ='Financial Statement Amazon'!D52 -> 18851 | E26: ='Financial Statement Amazon'!E52 -> 21493 | F26: ='Financial Statement Walmart'!B52 -> 6557 | G26: ='Financial Statement Walmart'!C52 -> 7419 | H26: ='Financial Statement Walmart'!D52 -> 7381 | I26: ='Financial Statement Walmart'!E52 -> 7379
A27: Total Operating Liabilities (B) | B27: =SUM(B23:B26) -> 96107 | C27: =SUM(C23:C26) -> 94021 | D27: =SUM(D23:D26) -> 103832 | E27: =SUM(E23:E26) -> 115856 | F27: =SUM(F23:F26) -> 92215 | G27: =SUM(G23:G26) -> 94119 | H27: =SUM(H23:H26) -> 97536 | I27: =SUM(I23:I26) -> 99654
A29: Net Operating Assets (A-B) | B29: =B20-B27 -> 221451 | C29: =C20-C27 -> 293970 | D29: =D20-D27 -> 330845 | E29: =E20-E27 -> 387589 | F29: =F20-F27 -> 124997 | G29: =G20-G27 -> 129284 | H29: =H20-H27 -> 136547 | I29: =I20-I27 -> 147891
B31: Amazon | F31: Walmart
B32: 2021 | C32: 2022 | D32: 2023 | E32: 2024 | F32: 2021 | G32: 2022 | H32: 2023 | I32: 2024
A33: short term Debt
A34: Debt in Current Liabilities | B34: ='Financial Statement Amazon'!B34 -> 17162 | C34: ='Financial Statement Amazon'!C34 -> 23120 | D34: ='Financial Statement Amazon'!D34 -> 19561 | E34: ='Financial Statement Amazon'!E34 -> 17401 | F34: ='Financial Statement Walmart'!B34 -> 5207 | G34: ='Financial Statement Walmart'!C34 -> 6603 | H34: ='Financial Statement Walmart'!D34 -> 6537 | I34: ='Financial Statement Walmart'!E34 -> 7965
A35: Long term Debt
A36: Debt - Notes | B36: ='Financial Statement Amazon'!B48 -> 49750 | C36: ='Financial Statement Amazon'!C48 -> 69500 | D36: ='Financial Statement Amazon'!D48 -> 66500 | E36: ='Financial Statement Amazon'!E48 -> 58000 | F36: ='Financial Statement Walmart'!B48 -> 34864 | G36: ='Financial Statement Walmart'!C48 -> 34649 | H36: ='Financial Statement Walmart'!D48 -> 36132 | I36: ='Financial Statement Walmart'!E48 -> 33401
A37: Total Debt | B37: =B34+B36 -> 66912 | C37: =C34+C36 -> 92620 | D37: =D34+D36 -> 86061 | E37: =E34+E36 -> 75401 | F37: =F34+F36 -> 40071 | G37: =G34+G36 -> 41252 | H37: =H34+H36 -> 42669 | I37: =I34+I36 -> 41366
A41: Non Operating Asset | B41: ='Financial Statement Amazon'!E7 -> 101449
A42: Non Operating Liablities | B42: ='Financial Statement Amazon'!E34+'Financial Statement Amazon'!E43 -> 155401
A43: NNO | B43: =B42-B41 -> 53952

Sheet Profitability Ratio Analysis
A2: Productivity Ratios Analysis
D3: Amazon | H3: Walmart
A4: Particular | E4: 2022 | F4: 2023 | G4: 2024 | H4: 2022 | I4: 2023 | J4: 2024
A6: Traditional Dupont Disaggregation
A7: Return On Earning | E7: ='Key Ratios'!B6 -> -0.019149595 | F7: ='Key Ratios'!C6 -> 0.17489753 | G7: ='Key Ratios'!D6 -> 0.24289682 | H7: ='Key Ratios'!E6 -> 0.13299553 | I7: ='Key Ratios'!F6 -> 0.17818188 | J7: ='Key Ratios'!G6 -> 0.20701923
A9: Return on Asset | E9: ='Key Ratios'!B11 -> -0.0061637818 | F9: ='Key Ratios'!C11 -> 0.061431821 | G9: ='Key Ratios'!D11 -> 0.10279437 | H9: ='Key Ratios'!E11 -> 0.047863262 | I9: ='Key Ratios'!F11 -> 0.06259534 | J9: ='Key Ratios'!G11 -> 0.075741102
A11: Financial leverage | E11: ='Key Ratios'!B82 -> 3.1067931 | F11: ='Key Ratios'!C82 -> 2.8470186 | G11: ='Key Ratios'!D82 -> 2.362939 | H11: ='Key Ratios'!E82 -> 2.7786558 | I11: ='Key Ratios'!F82 -> 2.8465678 | J11: ='Key Ratios'!G82 -> 2.7332481
A13: RNOA Disaggregation by NOPM And NOAT
A14: NOPM | E14: ='Key Ratios'!B87 -> 0.024120136 | F14: ='Key Ratios'!C87 -> 0.052064198 | G14: ='Key Ratios'!D87 -> 0.094319463 | H14: ='Key Ratios'!E87 -> 0.026063525 | I14: ='Key Ratios'!F87 -> 0.028736219 | J14: ='Key Ratios'!G87 -> 0.033354347
A16: NOAT | E16: ='Key Ratios'!B92 -> 1.9944201 | F16: ='Key Ratios'!C92 -> 1.8398566 | G16: ='Key Ratios'!D92 -> 1.7759711 | H16: ='Key Ratios'!E92 -> 2.3741616 | I16: ='Key Ratios'!F92 -> 5.0789245 | J16: ='Key Ratios'!G92 -> 5.1234431
A18: RNOA | E18: ='Key Ratios'!B16 -> 0.048105684 | F18: ='Key Ratios'!C16 -> 0.095790658 | G18: ='Key Ratios'!D16 -> 0.16750864 | H18: ='Key Ratios'!E16 -> 0.061879021 | I18: ='Key Ratios'!F16 -> 0.14594909 | J18: ='Key Ratios'!G16 -> 0.1708891
A20: Operating Efficiency
A22: Gross Profit Margin | E22: ='Key Ratios'!B97 -> 0.48654527 | F22: ='Key Ratios'!C97 -> 0.52240577 | G22: ='Key Ratios'!D97 -> 0.53880892 | H22: ='Key Ratios'!E97 -> 0.25589131 | I22: ='Key Ratios'!F97 -> 0.259313 | J22: ='Key Ratios'!G97 -> 0.26756096
A24: Operating Expenses Margin | E24: ='Key Ratios'!B102 -> 0.025111725 | F24: ='Key Ratios'!C102 -> 0.064220535 | G24: ='Key Ratios'!D102 -> 0.10884399 | H24: ='Key Ratios'!E102 -> 0.035817059 | I24: ='Key Ratios'!F102 -> 0.038277193 | J24: ='Key Ratios'!G102 -> 0.043325477
A26: Profit Margin | E26: ='Key Ratios'!B107 -> -0.005295895 | F26: ='Key Ratios'!C107 -> 0.052932836 | G26: ='Key Ratios'!D107 -> 0.092871172 | H26: ='Key Ratios'!E107 -> 0.019195341 | I26: ='Key Ratios'!F107 -> 0.024020615 | J26: ='Key Ratios'!G107 -> 0.02854101

Sheet Productivity Ratio Analysis
A1: Cash Conversion Cycle for Amazon
A3: Ratio | B3: Formulae | C3: 2022 | D3: =C3+1 -> 2023 | E3: =D3+1 -> 2024
A5: Days Sales outstanding | B5: 360*(Average Account Receivable/Sales) | C5: =360*('Key Ratios'!B25/'Key Ratios'!B24) -> 21.467636 | D5: =360*('Key Ratios'!C25/'Key Ratios'!C24) -> 25.585219 | E5: =360*('Key Ratios'!D25/'Key Ratios'!D24) -> 27.14281
A6: Days Inventories Outstanding | B6: 360*(Average Inventory/Sales) | C6: =360*('Key Ratios'!B20/'Key Ratios'!B24) -> 22.838693 | D6: =360*('Key Ratios'!C20/'Key Ratios'!C24) -> 20.600642 | E6: =360*('Key Ratios'!D20/'Key Ratios'!D24) -> 18.492662
A7: Days Payable Outstanding | B7: 360*(Average Account Payable/Sales) | C7: =360*('Key Ratios'!B30/'Key Ratios'!B24) -> 55.425024 | D7: =360*('Key Ratios'!C30/'Key Ratios'!C24) -> 51.54028 | E7: =360*('Key Ratios'!D30/'Key Ratios'!D24) -> 50.601873
A9: Cash Conversion Cycle | C9: =SUM(C5:C7) -> 99.731353 | D9: =SUM(D5:D7) -> 97.726141 | E9: =SUM(E5:E7) -> 96.237344
A12: Cash Conversion Cycle for Walmart
A14: Ratio | B14: Formulae | C14: 2022 | D14: =C14+1 -> 2023 | E14: =D14+1 -> 2024
A16: Days Sales outstanding | B16: 360*(Average Account Receivable/Sales) | C16: =360*('[1]Key Ratios'!H23/'[1]Key Ratios'!H22) -> 54.186486 | D16: =360*('[1]Key Ratios'!I23/'[1]Key Ratios'!I22) -> 55.481712 | E16: =360*('[1]Key Ratios'!J23/'[1]Key Ratios'!J22) -> 52.248376
A17: Days Inventories Outstanding | B17: 360*(Average Inventory/Sales) | C17: 0 | D17: 0 | E17: 0
A18: Days Payable Outstanding | B18: 360*(Average Account Payable/Sales) | C18: =360*('[1]Key Ratios'!H29/'[1]Key Ratios'!H22) -> 13.491892 | D18: =360*('[1]Key Ratios'!I29/'[1]Key Ratios'!I22) -> 12.62252 | E18: =360*('[1]Key Ratios'!J29/'[1]Key Ratios'!J22) -> 11.266376
A20: Cash Conversion Cycle | C20: =SUM(C16:C18) -> 67.678378 | D20: =SUM(D16:D18) -> 68.104231 | E20: =SUM(E16:E18) -> 63.514751

Sheet Liquidy Solvency Ratio
A1: Credit Rating for Amazon -Z -Score
A2: Particular | C2: Ratio | D2: weight | E2: Total
A4: Working Capital | B4: ='Key Ratios'!D60-'Key Ratios'!D61 -> 11436
A5: Total Asset | B5: ='Financial Statement Amazon'!E32 -> 624894 | C5: =B4/B5 -> 0.018300704 | D5: 1.2 | E5: =C5*D5 -> 0.021960845
A7: Retained Earnings | B7: ='Financial Statement Amazon'!E65 -> 172832
A8: Total Asset | B8: =B5 -> 624894 | C8: =B7/B8 -> 0.27657811 | D8: 1.4 | E8: =C8*D8 -> 0.38720935
A10: Earning Before Income and Tax | B10: ='Financial Statement Amazon'!E81 -> 69438
A11: Total Asset | B11: =B8 -> 624894 | C11: =B10/B11 -> 0.11111965 | D11: 3.3 | E11: =C11*D11 -> 0.36669483
A13: Market Value of Equity | B13: 2390000
A14: Total Liabilities | B14: ='Key Ratios'!D70 -> 338924 | C14: =B13/B14 -> 7.0517284 | D14: 0.6 | E14: =C14*D14 -> 4.231037
A16: Sales | B16: ='Financial Statement Amazon'!E73 -> 637959
A17: Total Asset | B17: =B11 -> 624894 | C17: =B16/B17 -> 1.0209075 | D17: 0.99 | E17: =C17*D17 -> 1.0106985
E19: =SUM(E5,E8,E11,E14,E17) -> 6.0176005

Sheet Valuation_DCF
A1: Valuation As per Discounted Cashflow Method(DCF)
H2: Sales growth rate = 2.5%
A3: Cost of Capital (WACC) | B3: 0.098 | D3: Terminal Growth Rate | F3: 0.03
B5: 2024 | C5: 2025 | D5: 2026 | E5: 2027 | F5: Terminal Growth
A7: Sales | B7: ='Financial Statement Amazon'!E73 -> 637959 | C7: =B7*(1+2.5%) -> 653907.97 | D7: =C7*(1+2.5%) -> 670255.67 | E7: =D7*(1+2.5%) -> 687012.07 | F7: =E7*(1+2.5%) -> 704187.37
A8: Net-Operating Profit After Tax | B8: ='Additional Calculation'!D10 -> 60171.95 | C8: 54379 | D8: 59863 | E8: 63458 | F8: 65362
A9: Net-Operating Asset | B9: ='Additional Calculation'!E29 -> 387589 | C9: =B9*109% -> 422472.01 | D9: =C9*102% -> 430921.45 | E9: =D9*102% -> 439539.88 | F9: =E9*102% -> 448330.68
A12: Increase in NOA | C12: =C9-B9 -> 34883.01 | D12: =D9-C9 -> 8449.4402 | E12: =E9-D9 -> 8618.429 | F12: =F9-E9 -> 8790.7976
A13: Free Cashflow | C13: =C8-C12 -> 19495.99 | D13: =D8-D12 -> 51413.56 | E13: =E8-E12 -> 54839.571 | F13: =F8-F12 -> 56571.202 | G13: =F13*(1+3%)/((9.8%-3%)) -> 856887.33
A14: Present Value of Horizon Freecashflow | C14: =C13/(1+$B$3)^1 -> 17755.911 | D14: =D13/(1+$B$3)^2 -> 42645.479 | E14: =E13/(1+$B$3)^3 -> 41427.338
A16: Cum.Present Value Of Horizon Free Cashflow | B16: =SUM(C14:E14) -> 101828.73
A17: Present Value Of Terminal Free cash flow | B17: =G13/(1+9.8%)^3 -> 647316.54
A18: Total Firm Value | B18: =B16+B17 -> 749145.26
A19: Net non-operating Obligation | B19: ='Additional Calculation'!B43 -> 53952
A20: Firm Equity Value | B20: =B18-B19 -> 695193.26
A21: Share Outstanding | B21: 10900
A22: Stock Price Per Share | B22: =B20/B21 -> 63.779198
